setup.py
fetch_aws_secrets_test/__init__.py
fetch_aws_secrets_test/athena_credentials.py
fetch_aws_secrets_test/database_credentials.py
fetch_aws_secrets_test/google_credentials.py
fetch_aws_secrets_test.egg-info/PKG-INFO
fetch_aws_secrets_test.egg-info/SOURCES.txt
fetch_aws_secrets_test.egg-info/dependency_links.txt
fetch_aws_secrets_test.egg-info/not-zip-safe
fetch_aws_secrets_test.egg-info/requires.txt
fetch_aws_secrets_test.egg-info/top_level.txt