Metadata-Version: 2.1
Name: fetch-aws-secrets-test
Version: 0.3
Summary: Use AWS defined function to fetch secrets and credentials
Home-page: https://github.com/GioDecio/fetch_aws_secrets_test
Author: Gpy
Author-email: giovanni.decillis@gmail.com
License: private
Platform: UNKNOWN
